MDAF_objective_functions/__init__.py
MDAF_objective_functions/default_settings.py
MDAF_objective_functions/objective_function.py
MDAF_objective_functions/implementations/__init__.py
MDAF_objective_functions/implementations/ackley.py
MDAF_objective_functions/implementations/bukin6.py
MDAF_objective_functions/implementations/drop_wave.py
MDAF_objective_functions/implementations/eggholder.py
MDAF_objective_functions/implementations/franke.py
MDAF_objective_functions/implementations/gramacy_and_lee.py
MDAF_objective_functions/implementations/griewank.py
MDAF_objective_functions/implementations/holder_table.py
MDAF_objective_functions/implementations/langermann.py
MDAF_objective_functions/implementations/levy.py
MDAF_objective_functions/implementations/michalewicz.py
MDAF_objective_functions/implementations/rastrigin.py
MDAF_objective_functions/implementations/rosenbrock.py
MDAF_objective_functions/implementations/six_hump_camel_back.py
MDAF_objective_functions/implementations/sphere.py
MDAF_objective_functions/implementations/styblinski_tang.py
MDAF_objective_functions/tmp/__init__.py
mdaf_objective_functions-0.1.0.dist-info/METADATA
mdaf_objective_functions-0.1.0.dist-info/WHEEL
mdaf_objective_functions-0.1.0.dist-info/top_level.txt
mdaf_objective_functions-0.1.0.dist-info/RECORD
