Metadata-Version: 2.4
Name: MDAF_objective_functions
Version: 0.1.0
Summary: A library for mathematical benchmark functions.
Author-email: Iannick Gagnon <iannick.gagnon@etsmtl.ca>
License: MIT
Requires-Python: >=3.8
Requires-Dist: autograd==1.6.2
Requires-Dist: cloudpickle==3.0.0
Requires-Dist: colorama==0.4.6
Requires-Dist: contourpy==1.2.1
Requires-Dist: cycler==0.12.1
Requires-Dist: dill==0.3.8
Requires-Dist: fonttools==4.51.0
Requires-Dist: future==1.0.0
Requires-Dist: iniconfig==2.0.0
Requires-Dist: kiwisolver==1.4.5
Requires-Dist: line_profiler==4.1.3
Requires-Dist: matplotlib==3.8.4
Requires-Dist: numpy==1.26.4
Requires-Dist: packaging==25.0
Requires-Dist: pandas==2.2.2
Requires-Dist: pillow==10.3.0
Requires-Dist: pluggy==1.5.0
Requires-Dist: pyparsing==3.1.2
Requires-Dist: pytest==8.2.0
Requires-Dist: python-dateutil==2.9.0.post0
Requires-Dist: pytz==2024.1
Requires-Dist: scipy==1.13.0
Requires-Dist: six==1.16.0
Requires-Dist: tzdata==2024.1
Provides-Extra: dev
